pyjiit/__init__.py
pyjiit/attendance.py
pyjiit/default.py
pyjiit/encryption.py
pyjiit/exam.py
pyjiit/exceptions.py
pyjiit/init.py
pyjiit/registration.py
pyjiit/tokens.py
pyjiit/utils.py
pyjiit/wrapper.py
pyjiit-0.1.0a8.dist-info/METADATA
pyjiit-0.1.0a8.dist-info/WHEEL
pyjiit-0.1.0a8.dist-info/licenses/LICENSE
pyjiit-0.1.0a8.dist-info/RECORD
