Metadata-Version: 2.4
Name: pyjiit
Version: 0.1.0a8
Summary: Python wrapper for JIIT webportal
License: MIT
License-File: LICENSE
Author: Harsh Sharma
Author-email: harsh@codelif.in
Requires-Python: >=3.9
Classifier: License :: OSI Approved :: MIT License
Classifier: Programming Language :: Python :: 3
Classifier: Programming Language :: Python :: 3.9
Classifier: Programming Language :: Python :: 3.10
Classifier: Programming Language :: Python :: 3.11
Classifier: Programming Language :: Python :: 3.12
Classifier: Programming Language :: Python :: 3.13
Classifier: Programming Language :: Python :: 3.14
Requires-Dist: pycryptodome (>=3.22.0,<4.0.0)
Requires-Dist: requests (>=2.32.3,<3.0.0)
Project-URL: Homepage, https://github.com/codelif/pyjiit
Project-URL: Issues, https://github.com/codelif/pyjiit/issues
